{
    "items": [
        {
            "publishers": [
                {
                    "publisher": {
                        "url": "http://www.hindawi.com/",
                        "country": "gb",
                        "id": 100,
                        "country_phrases": [
                            {
                                "phrase": "United Kingdom",
                                "language": "en",
                                "value": "gb"
                            }
                        ],
                        "identifiers": [
                            {
                                "type_phrases": [
                                    {
                                        "phrase": "ROR ID",
                                        "value": "ror",
                                        "language": "en"
                                    }
                                ],
                                "identifier": "https://ror.org/02rt9z237",
                                "type": "ror"
                            }
                        ],
                        "publication_count": 241,
                        "uri": "https://v2.sherpa.ac.uk/id/publisher/100",
                        "name": [
                            {
                                "name": "Hindawi",
                                "preferred": "name",
                                "language_phrases": [
                                    {
                                        "phrase": "English",
                                        "language": "en",
                                        "value": "en"
                                    }
                                ],
                                "language": "en",
                                "preferred_phrases": [
                                    {
                                        "phrase": "Name",
                                        "language": "en",
                                        "value": "name"
                                    }
                                ]
                            }
                        ],
                        "imprint_of_id": 580
                    },
                    "relationship_type_phrases": [
                        {
                            "phrase": "Commercial Publisher",
                            "language": "en",
                            "value": "commercial_publisher"
                        }
                    ],
                    "relationship_type": "commercial_publisher"
                }
            ],
            "url": "https://www.hindawi.com/journals/oti/",
            "type": "journal",
            "issns": [
                {
                    "issn": "0966-7903",
                    "type_phrases": [
                        {
                            "phrase": "Print",
                            "value": "print",
                            "language": "en"
                        }
                    ],
                    "type": "print"
                },
                {
                    "type_phrases": [
                        {
                            "language": "en",
                            "value": "electronic",
                            "phrase": "Electronic"
                        }
                    ],
                    "issn": "1557-0703",
                    "type": "electronic"
                }
            ],
            "title": [
                {
                    "language": "en",
                    "language_phrases": [
                        {
                            "phrase": "English",
                            "language": "en",
                            "value": "en"
                        }
                    ],
                    "preferred_phrases": [
                        {
                            "language": "en",
                            "value": "name",
                            "phrase": "Title"
                        }
                    ],
                    "title": "Occupational Therapy International",
                    "preferred": "name"
                }
            ],
            "listed_in_doaj_phrases": [
                {
                    "language": "en",
                    "value": "yes",
                    "phrase": "Yes"
                }
            ],
            "id": 7522,
            "publisher_policy": [
                {
                    "publication_count": 150,
                    "uri": "https://v2.sherpa.ac.uk/id/publisher_policy/4064",
                    "open_access_prohibited_phrases": [
                        {
                            "language": "en",
                            "value": "no",
                            "phrase": "No"
                        }
                    ],
                    "permitted_oa": [
                        {
                            "additional_oa_fee_phrases": [
                                {
                                    "phrase": "No",
                                    "value": "no",
                                    "language": "en"
                                }
                            ],
                            "article_version_phrases": [
                                {
                                    "phrase": "Published",
                                    "value": "published",
                                    "language": "en"
                                }
                            ],
                            "publisher_deposit": [
                                {
                                    "system_metadata": {
                                        "id": 267,
                                        "uri": "https://v2.sherpa.ac.uk/id/repository/267"
                                    },
                                    "repository_metadata": {
                                        "name": [
                                            {
                                                "language_phrases": [
                                                    {
                                                        "language": "en",
                                                        "value": "en",
                                                        "phrase": "English"
                                                    }
                                                ],
                                                "language": "en",
                                                "preferred_phrases": [
                                                    {
                                                        "language": "en",
                                                        "value": "name",
                                                        "phrase": "Name"
                                                    }
                                                ],
                                                "preferred": "name",
                                                "name": "PubMed Central"
                                            }
                                        ],
                                        "type_phrases": [
                                            {
                                                "language": "en",
                                                "value": "disciplinary",
                                                "phrase": "Disciplinary"
                                            }
                                        ],
                                        "url": "http://www.ncbi.nlm.nih.gov/pmc/",
                                        "type": "disciplinary"
                                    }
                                }
                            ],
                            "copyright_owner": "authors",
                            "license": [
                                {
                                    "version": "4.0",
                                    "license": "cc_by",
                                    "license_phrases": [
                                        {
                                            "phrase": "CC BY",
                                            "language": "en",
                                            "value": "cc_by"
                                        }
                                    ]
                                }
                            ],
                            "copyright_owner_phrases": [
                                {
                                    "value": "authors",
                                    "language": "en",
                                    "phrase": "Authors"
                                }
                            ],
                            "article_version": [
                                "published"
                            ],
                            "location": {
                                "location": [
                                    "any_website",
                                    "this_journal"
                                ],
                                "location_phrases": [
                                    {
                                        "language": "en",
                                        "value": "any_website",
                                        "phrase": "Any Website"
                                    },
                                    {
                                        "language": "en",
                                        "value": "this_journal",
                                        "phrase": "Journal Website"
                                    }
                                ]
                            },
                            "additional_oa_fee": "no",
                            "conditions": [
                                "Published source must be acknowledged with citation"
                            ]
                        },
                        {
                            "additional_oa_fee_phrases": [
                                {
                                    "value": "no",
                                    "language": "en",
                                    "phrase": "No"
                                }
                            ],
                            "license": [
                                {
                                    "license_phrases": [
                                        {
                                            "language": "en",
                                            "value": "cc_by",
                                            "phrase": "CC BY"
                                        }
                                    ],
                                    "license": "cc_by"
                                }
                            ],
                            "article_version_phrases": [
                                {
                                    "phrase": "Submitted",
                                    "language": "en",
                                    "value": "submitted"
                                },
                                {
                                    "phrase": "Accepted",
                                    "language": "en",
                                    "value": "accepted"
                                }
                            ],
                            "article_version": [
                                "submitted",
                                "accepted"
                            ],
                            "location": {
                                "location_phrases": [
                                    {
                                        "value": "any_website",
                                        "language": "en",
                                        "phrase": "Any Website"
                                    },
                                    {
                                        "value": "institutional_repository",
                                        "language": "en",
                                        "phrase": "Institutional Repository"
                                    },
                                    {
                                        "phrase": "Preprint Repository",
                                        "value": "preprint_repository",
                                        "language": "en"
                                    }
                                ],
                                "location": [
                                    "any_website",
                                    "institutional_repository",
                                    "preprint_repository"
                                ]
                            },
                            "additional_oa_fee": "no",
                            "conditions": [
                                "Published source must be acknowledged with citation"
                            ]
                        }
                    ],
                    "internal_moniker": "PubMed Central",
                    "id": 4064,
                    "open_access_prohibited": "no",
                    "urls": [
                        {
                            "description": "For Authors (Example)",
                            "url": "https://www.hindawi.com/journals/apm/guidelines/"
                        }
                    ]
                }
            ],
            "listed_in_doaj": "yes",
            "system_metadata": {
                "date_created": "2010-08-05 13:45:11",
                "date_modified": "2022-09-22 08:02:26",
                "publicly_visible_phrases": [
                    {
                        "phrase": "Yes",
                        "language": "en",
                        "value": "yes"
                    }
                ],
                "id": 7522,
                "uri": "https://v2.sherpa.ac.uk/id/publication/7522",
                "publicly_visible": "yes"
            },
            "type_phrases": [
                {
                    "phrase": "Journal",
                    "language": "en",
                    "value": "journal"
                }
            ]
        }
    ]
}