{
    "items": [
        {
            "system_metadata": {
                "publicly_visible": "yes",
                "date_modified": "2022-06-22 12:20:53",
                "uri": "https://v2.sherpa.ac.uk/id/publication/6843",
                "id": 6843,
                "date_created": "2010-08-04 09:34:40",
                "publicly_visible_phrases": [
                    {
                        "language": "en",
                        "phrase": "Yes",
                        "value": "yes"
                    }
                ]
            },
            "publisher_policy": [
                {
                    "uri": "https://v2.sherpa.ac.uk/id/publisher_policy/2197",
                    "urls": [
                        {
                            "description": "Authors' Rights (topiCS)",
                            "url": "https://cognitivesciencesociety.org/topics-journal/"
                        },
                        {
                            "url": "https://cognitivesciencesociety.org/cognitive-science-journal/",
                            "description": "Authors' Rights (Cognitive Science)"
                        }
                    ],
                    "id": 2197,
                    "open_access_prohibited": "no",
                    "open_access_prohibited_phrases": [
                        {
                            "phrase": "No",
                            "value": "no",
                            "language": "en"
                        }
                    ],
                    "internal_moniker": "0 months",
                    "permitted_oa": [
                        {
                            "article_version_phrases": [
                                {
                                    "language": "en",
                                    "phrase": "Published",
                                    "value": "published"
                                }
                            ],
                            "additional_oa_fee_phrases": [
                                {
                                    "language": "en",
                                    "phrase": "No",
                                    "value": "no"
                                }
                            ],
                            "additional_oa_fee": "no",
                            "copyright_owner_phrases": [
                                {
                                    "value": "learned_society",
                                    "phrase": "Learned Society",
                                    "language": "en"
                                }
                            ],
                            "id": 8120,
                            "copyright_owner": "learned_society",
                            "article_version": [
                                "published"
                            ],
                            "location": {
                                "location": [
                                    "authors_homepage"
                                ],
                                "location_phrases": [
                                    {
                                        "value": "authors_homepage",
                                        "phrase": "Author's Homepage",
                                        "language": "en"
                                    }
                                ]
                            }
                        },
                        {
                            "location": {
                                "location_phrases": [
                                    {
                                        "language": "en",
                                        "value": "this_journal",
                                        "phrase": "Journal Website"
                                    }
                                ],
                                "location": [
                                    "this_journal"
                                ]
                            },
                            "additional_oa_fee": "no",
                            "article_version_phrases": [
                                {
                                    "phrase": "Published",
                                    "value": "published",
                                    "language": "en"
                                }
                            ],
                            "additional_oa_fee_phrases": [
                                {
                                    "language": "en",
                                    "phrase": "No",
                                    "value": "no"
                                }
                            ],
                            "id": 9105,
                            "article_version": [
                                "published"
                            ],
                            "embargo": {
                                "units": "months",
                                "amount": 12,
                                "units_phrases": [
                                    {
                                        "language": "en",
                                        "value": "months",
                                        "phrase": "Months"
                                    }
                                ]
                            }
                        }
                    ],
                    "publication_count": 3
                },
                {
                    "permitted_oa": [
                        {
                            "publisher_deposit": [
                                {
                                    "system_metadata": {
                                        "id": 267,
                                        "uri": "https://v2.sherpa.ac.uk/id/repository/267"
                                    },
                                    "repository_metadata": {
                                        "url": "http://www.ncbi.nlm.nih.gov/pmc/",
                                        "name": [
                                            {
                                                "language": "en",
                                                "preferred_phrases": [
                                                    {
                                                        "phrase": "Name",
                                                        "value": "name",
                                                        "language": "en"
                                                    }
                                                ],
                                                "language_phrases": [
                                                    {
                                                        "language": "en",
                                                        "phrase": "English",
                                                        "value": "en"
                                                    }
                                                ],
                                                "name": "PubMed Central",
                                                "preferred": "name"
                                            }
                                        ],
                                        "type_phrases": [
                                            {
                                                "phrase": "Disciplinary",
                                                "value": "disciplinary",
                                                "language": "en"
                                            }
                                        ],
                                        "type": "disciplinary"
                                    }
                                },
                                {
                                    "repository_metadata": {
                                        "type_phrases": [
                                            {
                                                "phrase": "Disciplinary",
                                                "value": "disciplinary",
                                                "language": "en"
                                            }
                                        ],
                                        "url": "http://europepmc.org/",
                                        "name": [
                                            {
                                                "name": "Europe PMC",
                                                "preferred": "name",
                                                "language": "en",
                                                "language_phrases": [
                                                    {
                                                        "language": "en",
                                                        "phrase": "English",
                                                        "value": "en"
                                                    }
                                                ],
                                                "preferred_phrases": [
                                                    {
                                                        "language": "en",
                                                        "value": "name",
                                                        "phrase": "Name"
                                                    }
                                                ]
                                            }
                                        ],
                                        "type": "disciplinary",
                                        "notes": "Launched as UK PubMed Central (UKPMC) in January 2007, changed to Europe PubMed Central in November 2012.\r\nSpecial item types include: Links"
                                    },
                                    "system_metadata": {
                                        "uri": "https://v2.sherpa.ac.uk/id/repository/908",
                                        "id": 908
                                    }
                                }
                            ],
                            "location": {
                                "location_phrases": [
                                    {
                                        "language": "en",
                                        "phrase": "Any Repository",
                                        "value": "any_repository"
                                    },
                                    {
                                        "language": "en",
                                        "value": "any_website",
                                        "phrase": "Any Website"
                                    },
                                    {
                                        "language": "en",
                                        "value": "named_repository",
                                        "phrase": "Named Repository"
                                    },
                                    {
                                        "phrase": "Journal Website",
                                        "value": "this_journal",
                                        "language": "en"
                                    }
                                ],
                                "named_repository": [
                                    "PubMed Central"
                                ],
                                "location": [
                                    "any_repository",
                                    "any_website",
                                    "named_repository",
                                    "this_journal"
                                ]
                            },
                            "license": [
                                {
                                    "license_phrases": [
                                        {
                                            "language": "en",
                                            "phrase": "CC BY",
                                            "value": "cc_by"
                                        }
                                    ],
                                    "license": "cc_by"
                                }
                            ],
                            "copyright_owner": "authors",
                            "additional_oa_fee_phrases": [
                                {
                                    "value": "yes",
                                    "phrase": "Yes",
                                    "language": "en"
                                }
                            ],
                            "copyright_owner_phrases": [
                                {
                                    "language": "en",
                                    "value": "authors",
                                    "phrase": "Authors"
                                }
                            ],
                            "id": 157,
                            "article_version": [
                                "published"
                            ],
                            "additional_oa_fee": "yes",
                            "article_version_phrases": [
                                {
                                    "language": "en",
                                    "value": "published",
                                    "phrase": "Published"
                                }
                            ],
                            "conditions": [
                                "Published source must be acknowledged"
                            ]
                        },
                        {
                            "article_version_phrases": [
                                {
                                    "phrase": "Published",
                                    "value": "published",
                                    "language": "en"
                                }
                            ],
                            "additional_oa_fee": "yes",
                            "conditions": [
                                "Published source must be acknowledged"
                            ],
                            "id": 521,
                            "article_version": [
                                "published"
                            ],
                            "license": [
                                {
                                    "license_phrases": [
                                        {
                                            "language": "en",
                                            "value": "cc_by_nc_nd",
                                            "phrase": "CC BY-NC-ND"
                                        }
                                    ],
                                    "license": "cc_by_nc_nd"
                                }
                            ],
                            "location": {
                                "location_phrases": [
                                    {
                                        "value": "any_repository",
                                        "phrase": "Any Repository",
                                        "language": "en"
                                    },
                                    {
                                        "phrase": "Any Website",
                                        "value": "any_website",
                                        "language": "en"
                                    },
                                    {
                                        "language": "en",
                                        "value": "named_repository",
                                        "phrase": "Named Repository"
                                    },
                                    {
                                        "language": "en",
                                        "value": "this_journal",
                                        "phrase": "Journal Website"
                                    }
                                ],
                                "named_repository": [
                                    "PubMed Central"
                                ],
                                "location": [
                                    "any_repository",
                                    "any_website",
                                    "named_repository",
                                    "this_journal"
                                ]
                            },
                            "publisher_deposit": [
                                {
                                    "system_metadata": {
                                        "uri": "https://v2.sherpa.ac.uk/id/repository/267",
                                        "id": 267
                                    },
                                    "repository_metadata": {
                                        "type": "disciplinary",
                                        "name": [
                                            {
                                                "preferred_phrases": [
                                                    {
                                                        "language": "en",
                                                        "value": "name",
                                                        "phrase": "Name"
                                                    }
                                                ],
                                                "language_phrases": [
                                                    {
                                                        "language": "en",
                                                        "value": "en",
                                                        "phrase": "English"
                                                    }
                                                ],
                                                "language": "en",
                                                "preferred": "name",
                                                "name": "PubMed Central"
                                            }
                                        ],
                                        "url": "http://www.ncbi.nlm.nih.gov/pmc/",
                                        "type_phrases": [
                                            {
                                                "language": "en",
                                                "value": "disciplinary",
                                                "phrase": "Disciplinary"
                                            }
                                        ]
                                    }
                                },
                                {
                                    "system_metadata": {
                                        "uri": "https://v2.sherpa.ac.uk/id/repository/908",
                                        "id": 908
                                    },
                                    "repository_metadata": {
                                        "type": "disciplinary",
                                        "notes": "Launched as UK PubMed Central (UKPMC) in January 2007, changed to Europe PubMed Central in November 2012.\r\nSpecial item types include: Links",
                                        "type_phrases": [
                                            {
                                                "value": "disciplinary",
                                                "phrase": "Disciplinary",
                                                "language": "en"
                                            }
                                        ],
                                        "url": "http://europepmc.org/",
                                        "name": [
                                            {
                                                "preferred": "name",
                                                "name": "Europe PMC",
                                                "language_phrases": [
                                                    {
                                                        "phrase": "English",
                                                        "value": "en",
                                                        "language": "en"
                                                    }
                                                ],
                                                "preferred_phrases": [
                                                    {
                                                        "language": "en",
                                                        "phrase": "Name",
                                                        "value": "name"
                                                    }
                                                ],
                                                "language": "en"
                                            }
                                        ]
                                    }
                                }
                            ],
                            "additional_oa_fee_phrases": [
                                {
                                    "language": "en",
                                    "phrase": "Yes",
                                    "value": "yes"
                                }
                            ],
                            "copyright_owner_phrases": [
                                {
                                    "value": "authors",
                                    "phrase": "Authors",
                                    "language": "en"
                                }
                            ],
                            "copyright_owner": "authors"
                        },
                        {
                            "publisher_deposit": [
                                {
                                    "repository_metadata": {
                                        "type_phrases": [
                                            {
                                                "value": "disciplinary",
                                                "phrase": "Disciplinary",
                                                "language": "en"
                                            }
                                        ],
                                        "url": "http://www.ncbi.nlm.nih.gov/pmc/",
                                        "name": [
                                            {
                                                "language_phrases": [
                                                    {
                                                        "language": "en",
                                                        "value": "en",
                                                        "phrase": "English"
                                                    }
                                                ],
                                                "preferred_phrases": [
                                                    {
                                                        "language": "en",
                                                        "phrase": "Name",
                                                        "value": "name"
                                                    }
                                                ],
                                                "language": "en",
                                                "preferred": "name",
                                                "name": "PubMed Central"
                                            }
                                        ],
                                        "type": "disciplinary"
                                    },
                                    "system_metadata": {
                                        "id": 267,
                                        "uri": "https://v2.sherpa.ac.uk/id/repository/267"
                                    }
                                },
                                {
                                    "repository_metadata": {
                                        "type": "disciplinary",
                                        "notes": "Launched as UK PubMed Central (UKPMC) in January 2007, changed to Europe PubMed Central in November 2012.\r\nSpecial item types include: Links",
                                        "type_phrases": [
                                            {
                                                "value": "disciplinary",
                                                "phrase": "Disciplinary",
                                                "language": "en"
                                            }
                                        ],
                                        "name": [
                                            {
                                                "preferred": "name",
                                                "name": "Europe PMC",
                                                "language_phrases": [
                                                    {
                                                        "language": "en",
                                                        "phrase": "English",
                                                        "value": "en"
                                                    }
                                                ],
                                                "preferred_phrases": [
                                                    {
                                                        "language": "en",
                                                        "value": "name",
                                                        "phrase": "Name"
                                                    }
                                                ],
                                                "language": "en"
                                            }
                                        ],
                                        "url": "http://europepmc.org/"
                                    },
                                    "system_metadata": {
                                        "id": 908,
                                        "uri": "https://v2.sherpa.ac.uk/id/repository/908"
                                    }
                                }
                            ],
                            "license": [
                                {
                                    "license": "cc_by_nc",
                                    "license_phrases": [
                                        {
                                            "language": "en",
                                            "phrase": "CC BY-NC",
                                            "value": "cc_by_nc"
                                        }
                                    ]
                                }
                            ],
                            "location": {
                                "location": [
                                    "any_repository",
                                    "any_website",
                                    "named_repository",
                                    "this_journal"
                                ],
                                "location_phrases": [
                                    {
                                        "phrase": "Any Repository",
                                        "value": "any_repository",
                                        "language": "en"
                                    },
                                    {
                                        "value": "any_website",
                                        "phrase": "Any Website",
                                        "language": "en"
                                    },
                                    {
                                        "language": "en",
                                        "phrase": "Named Repository",
                                        "value": "named_repository"
                                    },
                                    {
                                        "phrase": "Journal Website",
                                        "value": "this_journal",
                                        "language": "en"
                                    }
                                ],
                                "named_repository": [
                                    "PubMed Central"
                                ]
                            },
                            "copyright_owner": "authors",
                            "copyright_owner_phrases": [
                                {
                                    "phrase": "Authors",
                                    "value": "authors",
                                    "language": "en"
                                }
                            ],
                            "additional_oa_fee_phrases": [
                                {
                                    "value": "yes",
                                    "phrase": "Yes",
                                    "language": "en"
                                }
                            ],
                            "article_version": [
                                "published"
                            ],
                            "id": 8047,
                            "conditions": [
                                "Published source must be acknowledged"
                            ],
                            "additional_oa_fee": "yes",
                            "article_version_phrases": [
                                {
                                    "value": "published",
                                    "phrase": "Published",
                                    "language": "en"
                                }
                            ]
                        }
                    ],
                    "publication_count": 1223,
                    "internal_moniker": "Online Open",
                    "open_access_prohibited_phrases": [
                        {
                            "phrase": "No",
                            "value": "no",
                            "language": "en"
                        }
                    ],
                    "open_access_prohibited": "no",
                    "id": 3315,
                    "urls": [
                        {
                            "description": "Make your article open access in hybrid journals",
                            "url": "https://authorservices.wiley.com/author-resources/Journal-Authors/open-access/onlineopen.html"
                        },
                        {
                            "description": "Publishing Gold Open Access With Wiley",
                            "url": "https://www.wiley.com/network/researchers/researcher/publishing-gold-open-access-with-wiley"
                        }
                    ],
                    "uri": "https://v2.sherpa.ac.uk/id/publisher_policy/3315"
                }
            ],
            "issns": [
                {
                    "type": "print",
                    "issn": "0364-0213",
                    "type_phrases": [
                        {
                            "phrase": "Print",
                            "value": "print",
                            "language": "en"
                        }
                    ]
                },
                {
                    "issn": "1551-6709",
                    "type_phrases": [
                        {
                            "phrase": "Electronic",
                            "value": "electronic",
                            "language": "en"
                        }
                    ],
                    "type": "electronic"
                }
            ],
            "id": 6843,
            "type": "journal",
            "listed_in_doaj": "no",
            "publishers": [
                {
                    "relationship_type_phrases": [
                        {
                            "value": "commercial_publisher",
                            "phrase": "Commercial Publisher",
                            "language": "en"
                        }
                    ],
                    "relationship_type": "commercial_publisher",
                    "publisher": {
                        "id": 580,
                        "uri": "https://v2.sherpa.ac.uk/id/publisher/580",
                        "country_phrases": [
                            {
                                "value": "us",
                                "phrase": "United States of America",
                                "language": "en"
                            }
                        ],
                        "url": "https://www.wiley.com/en-gb",
                        "identifiers": [
                            {
                                "type": "ror",
                                "type_phrases": [
                                    {
                                        "language": "en",
                                        "phrase": "ROR ID",
                                        "value": "ror"
                                    }
                                ],
                                "identifier": "https://ror.org/01zm94433"
                            }
                        ],
                        "country": "us",
                        "name": [
                            {
                                "name": "Wiley",
                                "language_phrases": [
                                    {
                                        "value": "en",
                                        "phrase": "English",
                                        "language": "en"
                                    }
                                ],
                                "language": "en"
                            }
                        ],
                        "publication_count": 1388,
                        "imprints_id": [
                            1390,
                            100,
                            1032,
                            79
                        ]
                    }
                }
            ],
            "url": "https://onlinelibrary.wiley.com/journal/15516709",
            "listed_in_doaj_phrases": [
                {
                    "language": "en",
                    "phrase": "No",
                    "value": "no"
                }
            ],
            "title": [
                {
                    "language": "en",
                    "language_phrases": [
                        {
                            "language": "en",
                            "phrase": "English",
                            "value": "en"
                        }
                    ],
                    "title": "Cognitive Science: A Multidisciplinary Journal"
                }
            ],
            "type_phrases": [
                {
                    "language": "en",
                    "value": "journal",
                    "phrase": "Journal"
                }
            ]
        }
    ]
}