{
    "items": [
        {
            "publishers": [
                {
                    "relationship_type_phrases": [
                        {
                            "language": "en",
                            "value": "commercial_publisher",
                            "phrase": "Commercial Publisher"
                        }
                    ],
                    "publisher": {
                        "id": 62039,
                        "uri": "https://v2.sherpa.ac.uk/id/publisher/62039",
                        "url": "https://taylorandfrancis.com/",
                        "country_phrases": [
                            {
                                "phrase": "United Kingdom",
                                "value": "gb",
                                "language": "en"
                            }
                        ],
                        "imprint_of_id": 62038,
                        "country": "gb",
                        "imprints_id": [
                            407,
                            132,
                            193,
                            76
                        ],
                        "name": [
                            {
                                "language": "en",
                                "preferred_phrases": [
                                    {
                                        "language": "en",
                                        "value": "name",
                                        "phrase": "Name"
                                    }
                                ],
                                "language_phrases": [
                                    {
                                        "language": "en",
                                        "phrase": "English",
                                        "value": "en"
                                    }
                                ],
                                "name": "Taylor and Francis Group",
                                "preferred": "name"
                            }
                        ],
                        "publication_count": 2609
                    },
                    "relationship_type": "commercial_publisher"
                },
                {
                    "relationship_type_phrases": [
                        {
                            "language": "en",
                            "phrase": "Imprint",
                            "value": "imprint"
                        }
                    ],
                    "relationship_type": "imprint",
                    "publisher": {
                        "country_phrases": [
                            {
                                "phrase": "United Kingdom",
                                "value": "gb",
                                "language": "en"
                            }
                        ],
                        "url": "https://taylorandfrancis.com/",
                        "uri": "https://v2.sherpa.ac.uk/id/publisher/76",
                        "id": 76,
                        "publication_count": 925,
                        "name": [
                            {
                                "name": "Taylor and Francis",
                                "preferred": "name",
                                "language": "en",
                                "language_phrases": [
                                    {
                                        "language": "en",
                                        "phrase": "English",
                                        "value": "en"
                                    }
                                ],
                                "preferred_phrases": [
                                    {
                                        "value": "name",
                                        "phrase": "Name",
                                        "language": "en"
                                    }
                                ]
                            }
                        ],
                        "imprints_id": [
                            1546
                        ],
                        "country": "gb",
                        "imprint_of_id": 62039
                    }
                }
            ],
            "listed_in_doaj": "yes",
            "listed_in_doaj_phrases": [
                {
                    "phrase": "Yes",
                    "value": "yes",
                    "language": "en"
                }
            ],
            "url": "https://www.tandfonline.com/journals/ZMEO",
            "title": [
                {
                    "preferred": "name",
                    "title": "Medical Education Online",
                    "preferred_phrases": [
                        {
                            "language": "en",
                            "phrase": "Title",
                            "value": "name"
                        }
                    ],
                    "acronym": "MEO",
                    "language_phrases": [
                        {
                            "language": "en",
                            "value": "en",
                            "phrase": "English"
                        }
                    ],
                    "language": "en"
                }
            ],
            "type_phrases": [
                {
                    "language": "en",
                    "value": "journal",
                    "phrase": "Journal"
                }
            ],
            "publisher_policy": [
                {
                    "permitted_oa": [
                        {
                            "additional_oa_fee_phrases": [
                                {
                                    "phrase": "No",
                                    "value": "no",
                                    "language": "en"
                                }
                            ],
                            "copyright_owner_phrases": [
                                {
                                    "language": "en",
                                    "value": "authors",
                                    "phrase": "Authors"
                                }
                            ],
                            "copyright_owner": "authors",
                            "publisher_deposit": [
                                {
                                    "repository_metadata": {
                                        "name": [
                                            {
                                                "preferred_phrases": [
                                                    {
                                                        "value": "name",
                                                        "phrase": "Name",
                                                        "language": "en"
                                                    }
                                                ],
                                                "language_phrases": [
                                                    {
                                                        "language": "en",
                                                        "phrase": "English",
                                                        "value": "en"
                                                    }
                                                ],
                                                "language": "en",
                                                "preferred": "name",
                                                "name": "PubMed Central"
                                            }
                                        ],
                                        "url": "http://www.ncbi.nlm.nih.gov/pmc/",
                                        "type_phrases": [
                                            {
                                                "language": "en",
                                                "value": "disciplinary",
                                                "phrase": "Disciplinary"
                                            }
                                        ],
                                        "type": "disciplinary"
                                    },
                                    "system_metadata": {
                                        "id": 267,
                                        "uri": "https://v2.sherpa.ac.uk/id/repository/267"
                                    }
                                }
                            ],
                            "license": [
                                {
                                    "license": "cc_by",
                                    "license_phrases": [
                                        {
                                            "language": "en",
                                            "phrase": "CC BY",
                                            "value": "cc_by"
                                        }
                                    ]
                                },
                                {
                                    "license": "cc_by_nc",
                                    "license_phrases": [
                                        {
                                            "phrase": "CC BY-NC",
                                            "value": "cc_by_nc",
                                            "language": "en"
                                        }
                                    ]
                                }
                            ],
                            "location": {
                                "location": [
                                    "any_website",
                                    "this_journal"
                                ],
                                "location_phrases": [
                                    {
                                        "language": "en",
                                        "value": "any_website",
                                        "phrase": "Any Website"
                                    },
                                    {
                                        "language": "en",
                                        "value": "this_journal",
                                        "phrase": "Journal Website"
                                    }
                                ]
                            },
                            "additional_oa_fee": "no",
                            "article_version_phrases": [
                                {
                                    "language": "en",
                                    "phrase": "Published",
                                    "value": "published"
                                }
                            ],
                            "conditions": [
                                "Published copyright and source must be acknowledged with citation",
                                "Must link to published article with DOI",
                                "Article will be automatically deposited in subject-based repositories"
                            ],
                            "id": 5709,
                            "article_version": [
                                "published"
                            ]
                        }
                    ],
                    "publication_count": 44,
                    "internal_moniker": "Creative Commons Attribution and Creative Commons Attribution Non-Commercial",
                    "open_access_prohibited_phrases": [
                        {
                            "language": "en",
                            "phrase": "No",
                            "value": "no"
                        }
                    ],
                    "open_access_prohibited": "no",
                    "id": 4181,
                    "urls": [
                        {
                            "description": "Publishing your research open access",
                            "url": "https://authorservices.taylorandfrancis.com/publishing-open-access/"
                        }
                    ],
                    "uri": "https://v2.sherpa.ac.uk/id/publisher_policy/4181"
                },
                {
                    "permitted_oa": [
                        {
                            "conditions": [
                                "Published source must be acknowledged with citation",
                                "Recommended to link to published article with DOI",
                                "Set statement to accompany deposit"
                            ],
                            "article_version_phrases": [
                                {
                                    "value": "accepted",
                                    "phrase": "Accepted",
                                    "language": "en"
                                }
                            ],
                            "additional_oa_fee": "no",
                            "article_version": [
                                "accepted"
                            ],
                            "id": 8607,
                            "location": {
                                "location": [
                                    "any_website",
                                    "named_repository"
                                ],
                                "location_phrases": [
                                    {
                                        "language": "en",
                                        "phrase": "Any Website",
                                        "value": "any_website"
                                    },
                                    {
                                        "phrase": "Named Repository",
                                        "value": "named_repository",
                                        "language": "en"
                                    }
                                ],
                                "named_repository": [
                                    "PubMed Central"
                                ]
                            },
                            "license": [
                                {
                                    "license": "cc_by_nc",
                                    "license_phrases": [
                                        {
                                            "language": "en",
                                            "value": "cc_by_nc",
                                            "phrase": "CC BY-NC"
                                        }
                                    ]
                                },
                                {
                                    "license": "cc_by_nc_nd",
                                    "license_phrases": [
                                        {
                                            "language": "en",
                                            "value": "cc_by_nc_nd",
                                            "phrase": "CC BY-NC-ND"
                                        }
                                    ]
                                }
                            ],
                            "prerequisites": {
                                "prerequisite_funders": [
                                    {
                                        "funder_metadata": {
                                            "identifiers": [
                                                {
                                                    "type": "fundref",
                                                    "type_phrases": [
                                                        {
                                                            "phrase": "FundRef DOI",
                                                            "value": "fundref",
                                                            "language": "en"
                                                        }
                                                    ],
                                                    "identifier": "http://dx.doi.org/10.13039/100000002"
                                                },
                                                {
                                                    "type": "ror",
                                                    "type_phrases": [
                                                        {
                                                            "value": "ror",
                                                            "phrase": "ROR ID",
                                                            "language": "en"
                                                        }
                                                    ],
                                                    "identifier": "https://ror.org/01cwqze88"
                                                }
                                            ],
                                            "url": [
                                                {
                                                    "language": "en",
                                                    "language_phrases": [
                                                        {
                                                            "phrase": "English",
                                                            "value": "en",
                                                            "language": "en"
                                                        }
                                                    ],
                                                    "url": "https://www.nih.gov/"
                                                }
                                            ],
                                            "name": [
                                                {
                                                    "language_phrases": [
                                                        {
                                                            "value": "en",
                                                            "phrase": "English",
                                                            "language": "en"
                                                        }
                                                    ],
                                                    "acronym": "NIH",
                                                    "preferred_phrases": [
                                                        {
                                                            "language": "en",
                                                            "phrase": "Name",
                                                            "value": "name"
                                                        }
                                                    ],
                                                    "language": "en",
                                                    "preferred": "name",
                                                    "name": "National Institutes of Health"
                                                }
                                            ],
                                            "country_phrases": [
                                                {
                                                    "language": "en",
                                                    "value": "us",
                                                    "phrase": "United States of America"
                                                }
                                            ],
                                            "id": 9,
                                            "country": "us"
                                        },
                                        "system_metadata": {
                                            "uri": "https://v2.sherpa.ac.uk/id/funder/9",
                                            "id": 9
                                        }
                                    }
                                ]
                            },
                            "copyright_owner_phrases": [
                                {
                                    "phrase": "Authors",
                                    "value": "authors",
                                    "language": "en"
                                }
                            ],
                            "additional_oa_fee_phrases": [
                                {
                                    "value": "no",
                                    "phrase": "No",
                                    "language": "en"
                                }
                            ],
                            "copyright_owner": "authors"
                        },
                        {
                            "license": [
                                {
                                    "license": "cc_by_nc",
                                    "license_phrases": [
                                        {
                                            "phrase": "CC BY-NC",
                                            "value": "cc_by_nc",
                                            "language": "en"
                                        }
                                    ]
                                },
                                {
                                    "license_phrases": [
                                        {
                                            "value": "cc_by_nc_nd",
                                            "phrase": "CC BY-NC-ND",
                                            "language": "en"
                                        }
                                    ],
                                    "license": "cc_by_nc_nd"
                                }
                            ],
                            "location": {
                                "location": [
                                    "any_website"
                                ],
                                "location_phrases": [
                                    {
                                        "value": "any_website",
                                        "phrase": "Any Website",
                                        "language": "en"
                                    }
                                ]
                            },
                            "additional_oa_fee": "no",
                            "additional_oa_fee_phrases": [
                                {
                                    "language": "en",
                                    "value": "no",
                                    "phrase": "No"
                                }
                            ],
                            "article_version_phrases": [
                                {
                                    "value": "submitted",
                                    "phrase": "Submitted",
                                    "language": "en"
                                },
                                {
                                    "language": "en",
                                    "phrase": "Accepted",
                                    "value": "accepted"
                                }
                            ],
                            "conditions": [
                                "Published source must be acknowledged with citation",
                                "Recommended to link to published article with DOI",
                                "Set statement to accompany deposit"
                            ],
                            "copyright_owner_phrases": [
                                {
                                    "phrase": "Authors",
                                    "value": "authors",
                                    "language": "en"
                                }
                            ],
                            "copyright_owner": "authors",
                            "id": 8608,
                            "article_version": [
                                "submitted",
                                "accepted"
                            ]
                        }
                    ],
                    "publication_count": 269,
                    "uri": "https://v2.sherpa.ac.uk/id/publisher_policy/6030",
                    "urls": [
                        {
                            "url": "https://authorservices.taylorandfrancis.com/publishing-open-access/",
                            "description": "Choose Open Access when publishing your research"
                        }
                    ],
                    "id": 6030,
                    "open_access_prohibited": "no",
                    "open_access_prohibited_phrases": [
                        {
                            "value": "no",
                            "phrase": "No",
                            "language": "en"
                        }
                    ],
                    "internal_moniker": "Accepted and Submitted (0 months)"
                }
            ],
            "issns": [
                {
                    "issn": "1087-2981",
                    "type_phrases": [
                        {
                            "language": "en",
                            "value": "electronic",
                            "phrase": "Electronic"
                        }
                    ],
                    "type": "electronic"
                }
            ],
            "system_metadata": {
                "uri": "https://v2.sherpa.ac.uk/id/publication/12692",
                "id": 12692,
                "date_modified": "2022-07-22 09:47:38",
                "publicly_visible": "yes",
                "publicly_visible_phrases": [
                    {
                        "language": "en",
                        "value": "yes",
                        "phrase": "Yes"
                    }
                ],
                "date_created": "2010-09-01 09:48:09"
            },
            "type": "journal",
            "id": 12692
        }
    ]
}